enos/__init__.py
enos/core/MqttClient.py
enos/core/__init__.py
enos/core/constant/ArrivedTopicPattern.py
enos/core/constant/DeliveryTopicFormat.py
enos/core/constant/DeviceCredential.py
enos/core/constant/FieldConstants.py
enos/core/constant/MethodConstants.py
enos/core/constant/OTAUpdateFailureCause.py
enos/core/constant/ResponseCode.py
enos/core/constant/__init__.py
enos/core/exception/EnvisionError.py
enos/core/exception/EnvisionException.py
enos/core/exception/__init__.py
enos/core/internal/Ciphers.py
enos/core/internal/DecoderRegistry.py
enos/core/internal/DefaultProcessor.py
enos/core/internal/MqttConnection.py
enos/core/internal/Profile.py
enos/core/internal/ResponseToken.py
enos/core/internal/SecureMode.py
enos/core/internal/__init__.py
enos/core/login/BaseLogin.py
enos/core/login/DynamicActivationLogin.py
enos/core/login/MessageIntegrationLogin.py
enos/core/login/NormalDeviceLogin.py
enos/core/login/__init__.py
enos/core/message/BaseCommand.py
enos/core/message/BaseReply.py
enos/core/message/BaseRequest.py
enos/core/message/BaseResponse.py
enos/core/message/IArrivedMessage.py
enos/core/message/IConnectCallback.py
enos/core/message/IMessageHandler.py
enos/core/message/IResponseCallback.py
enos/core/message/__init__.py
enos/core/message/body/AckMessageBody.py
enos/core/message/body/AnswerableMessageBody.py
enos/core/message/body/__init__.py
enos/core/util/CheckUtil.py
enos/core/util/ConcurrentDict.py
enos/core/util/ConcurrentSet.py
enos/core/util/Deprecation.py
enos/core/util/SignUtil.py
enos/core/util/StringI18n.py
enos/core/util/StringUtil.py
enos/core/util/__init__.py
enos/message/__init__.py
enos/message/downstream/__init__.py
enos/message/downstream/activate/DeviceActivateCommand.py
enos/message/downstream/activate/DeviceActivateReply.py
enos/message/downstream/activate/__init__.py
enos/message/downstream/device/SubDeviceDeleteCommand.py
enos/message/downstream/device/SubDeviceDeleteReply.py
enos/message/downstream/device/SubDeviceDisableCommand.py
enos_mqtt_sdk_python-0.1.1.dist-info/METADATA
enos_mqtt_sdk_python-0.1.1.dist-info/WHEEL
enos_mqtt_sdk_python-0.1.1.dist-info/top_level.txt
enos_mqtt_sdk_python-0.1.1.dist-info/RECORD
