Metadata-Version: 2.1
Name: enos-mqtt-sdk-python
Version: 0.1.1
Summary: EnOS MQTT SDK for Python
Home-page: UNKNOWN
Author: EnvisionIot
Author-email: 
License: UNKNOWN
Platform: UNKNOWN
Classifier: Programming Language :: Python :: 3
Classifier: Operating System :: OS Independent
Requires-Dist: paho-mqtt (>=1.4.0)
Requires-Dist: certifi
Requires-Dist: futures ; python_version == "2.7"
